{
  "onboarding_checklist": [
    {
      "question": "Você conseguiu instalar o Flutter na versão especificada no pubspec.yaml?",
      "type": "boolean"
    },
    {
      "question": "Você conseguiu configurar o Dart SDK corretamente?",
      "type": "boolean"
    },
    {
      "question": "Você conseguiu instalar as dependências do projeto via 'flutter pub get'?",
      "type": "boolean"
    },
    {
      "question": "Você conseguiu configurar as variáveis de ambiente corretamente?",
      "type": "boolean"
    },
    {
      "question": "Você conseguiu compilar o projeto sem erros?",
      "type": "boolean"
    },
    {
      "question": "Você conseguiu executar os testes unitários e de integração sem falhas?",
      "type": "boolean"
    },
    {
      "question": "Você conseguiu executar o aplicativo no emulador ou dispositivo físico?",
      "type": "boolean"
    },
    {
      "question": "Houve alguma dúvida durante o processo de onboarding? Qual?",
      "type": "text"
    },
    {
      "question": "Encontrou algum erro ou problema durante a configuração ou execução do projeto? Qual?",
      "type": "text"
    },
    {
      "question": "Comentários adicionais ou sugestões de melhoria no processo de onboarding",
      "type": "text"
    }
  ]
}
